beepberry/__init__.py
beepberry_lib-0.0.2.dist-info/METADATA
beepberry_lib-0.0.2.dist-info/WHEEL
beepberry_lib-0.0.2.dist-info/top_level.txt
beepberry_lib-0.0.2.dist-info/RECORD
