Metadata-Version: 2.1
Name: beepberry-lib
Version: 0.0.2
Summary: PythonLib for BEEPBERRY
Home-page: https://github.com/Xgorobot/XGO-PythonLib
Author: jd3096
Author-email: 1091329318@qq.com
License: MIT
Classifier: License :: OSI Approved :: MIT License
Classifier: Programming Language :: Python
Classifier: Programming Language :: Python :: 3
Classifier: Programming Language :: Python :: 3.6
Classifier: Programming Language :: Python :: Implementation :: CPython
Classifier: Programming Language :: Python :: Implementation :: PyPy
Requires-Python: >=3.6.0
